cli/__init__.py
cli/cli.py
cloud2earth/__init__.py
cloud2earth/core.py
cloud2earth/helpers.py
cloud2earth-1.0.0.dist-info/METADATA
cloud2earth-1.0.0.dist-info/WHEEL
cloud2earth-1.0.0.dist-info/entry_points.txt
cloud2earth-1.0.0.dist-info/top_level.txt
cloud2earth-1.0.0.dist-info/RECORD
